dialogchain/__init__.py
dialogchain/cli.py
dialogchain/config.py
dialogchain/connectors/__init__.py
dialogchain/connectors/base.py
dialogchain/connectors/destinations/__init__.py
dialogchain/connectors/destinations/email.py
dialogchain/connectors/destinations/file.py
dialogchain/connectors/destinations/http.py
dialogchain/connectors/destinations/log.py
dialogchain/connectors/sources/__init__.py
dialogchain/connectors/sources/file.py
dialogchain/connectors/sources/imap.py
dialogchain/connectors/sources/rtsp.py
dialogchain/connectors/sources/timer.py
dialogchain/connectors.py
dialogchain/core/__init__.py
dialogchain/core/connector.py
dialogchain/core/engine.py
dialogchain/core/processor.py
dialogchain/core/route.py
dialogchain/core/routes.py
dialogchain/core/tasks.py
dialogchain/destinations/__init__.py
dialogchain/destinations/base.py
dialogchain/destinations/log.py
dialogchain/engine.py
dialogchain/exceptions.py
dialogchain/processors/__init__.py
dialogchain/processors/base.py
dialogchain/processors/transform.py
dialogchain/processors.py
dialogchain/py.typed
dialogchain/scanner/__init__.py
dialogchain/scanner/base.py
dialogchain/scanner/file_scanner.py
dialogchain/scanner/http_scanner.py
dialogchain/scanner/migrate.py
dialogchain/scanner/network_scanner.py
dialogchain/scanner.py
dialogchain/sources/__init__.py
dialogchain/sources/base.py
dialogchain/sources/timer.py
dialogchain/utils/__init__.py
dialogchain/utils/core.py
dialogchain/utils/detect_objects.py
dialogchain/utils/extract_markdown.py
dialogchain/utils/logger.py
dialogchain/utils/process_markdown.py
dialogchain/utils/process_markdown_blocks.py
dialogchain/utils/template.py
dialogchain/utils.py
dialogchain-0.1.17.dist-info/LICENSE
dialogchain-0.1.17.dist-info/METADATA
dialogchain-0.1.17.dist-info/WHEEL
dialogchain-0.1.17.dist-info/entry_points.txt
dialogchain-0.1.17.dist-info/RECORD
