Metadata-Version: 2.3
Name: dialogchain
Version: 0.1.17
Summary: DialogChain - A flexible and extensible dialog processing framework
License: Apache-2.0
Author: Tom Sapletta
Author-email: info@softreck.dev
Requires-Python: >=3.8.1,<4.0.0
Classifier: Development Status :: 4 - Beta
Classifier: Intended Audience :: Developers
Classifier: License :: OSI Approved :: Apache Software License
Classifier: Programming Language :: Python :: 3
Classifier: Programming Language :: Python :: 3.9
Classifier: Programming Language :: Python :: 3.10
Classifier: Programming Language :: Python :: 3.11
Classifier: Programming Language :: Python :: 3.12
Classifier: Programming Language :: Python :: 3.13
Classifier: Programming Language :: Python :: 3.8
Classifier: Topic :: Communications :: Chat
Classifier: Topic :: Scientific/Engineering :: Artificial Intelligence
Classifier: Topic :: Software Development :: Libraries :: Python Modules
Classifier: Topic :: Text Processing :: Linguistic
Requires-Dist: aiofiles (>=24.1.0,<25.0.0)
Requires-Dist: aiohttp (>=3.8.0,<4.0.0)
Requires-Dist: asyncio-mqtt (>=0.13.0,<0.14.0)
Requires-Dist: click (>=8.0.0,<9.0.0)
Requires-Dist: grpcio (>=1.50.0,<2.0.0)
Requires-Dist: grpcio-tools (>=1.50.0,<2.0.0)
Requires-Dist: jinja2 (>=3.1.0,<4.0.0)
Requires-Dist: numpy (>=1.21.0,<2.0.0)
Requires-Dist: opencv-python (>=4.7.0,<5.0.0)
Requires-Dist: python-dotenv (>=1.0.0,<2.0.0)
Requires-Dist: python-nmap (>=0.7.1,<0.8.0)
Requires-Dist: pyyaml (>=6.0.0,<7.0.0)
Requires-Dist: ultralytics (>=8.3.146,<9.0.0)
Project-URL: Documentation, https://github.com/dialogchain/python
Project-URL: Homepage, https://github.com/dialogchain/python
Project-URL: Repository, https://github.com/dialogchain/python
